pyselmr-0.2.0.dist-info/METADATA
pyselmr-0.2.0.dist-info/WHEEL
selmr/__init__.py
selmr/selmr.cp310-win_amd64.pyd
pyselmr-0.2.0.dist-info/RECORD
